{
  "iso2": "BS",
  "title": "バハマ",
  "url": "https://ja.wikipedia.org/wiki/%E3%83%90%E3%83%8F%E3%83%9E",
  "article_length": 4275,
  "article": "バハマ国（バハマこく、（英語: Commonwealth of The Bahamas） 通称バハマは、西インド諸島のバハマ諸島を領有する国家。英語圏に属し、イギリス連邦の加盟国であると同時に英連邦王国の一国たる立憲君主制国家である。\n島国であり、海を隔てて北西にアメリカ合衆国のフロリダ半島が、南西にキューバが、南東にハイチが存在する。首都はニュー・プロビデンス島のナッソー。バハマ文書が注目を浴びている。人口は40万516人（2022年時点）。\n\n\n== 国名 ==\n正式名称は Commonwealth of The Bahamas（英語: コムンウェルス・オブ・ザ・バハーマズ）、通称はThe Bahamas [bəˈhɑːməz] ( 音声ファイル)。日本語の表記はバハマ国、通称はバハマ。\n名称に定冠詞を含む国のひとつで、国際連合バハマ常駐大使が確認した2025年4月10日付の書簡によると、アルファベット順などの一部の例外を除き、「The Bahamas（Tは原則大文字）」と表記する決まりとなっている。\n国名の語源は、スペイン語のバハマール（スペイン語: Baja mar、水位の下がった海、引き潮）から転じたという説が有力。\n英語の「Commonwealth」は多義語であるが、バハマの場合は、同じ政体名を持ち連邦制をとるオーストラリア連邦と異なり、「イギリス連邦を構成する国」という意味合いであり、共和国や連邦といった意味はもたない。\n\n\n== 歴史 ==\n\n先住民のアラワク族が定住していた土地に、1492年10月12日、イタリア人クリストファー・コロンブスが到達。上陸した島がサン・サルバドル島（サマナ島という島であったとする説もある）と名づけられた。これがコロンブスによる新大陸の発見となる。\nコロンブスの開いたスペインからバハマのルートを通って、多くのヨーロッパ人がやってくると、島にいた先住民のインディオは強制労働やヨーロッパ人が持ち込んだ疫病などで死に絶えてしまった。16世紀には、絶滅したインディオの代わりにアフリカから初めて、奴隷として多くの黒人がバハマ諸島に連れてこられた。\n\n\n=== 年表 ===\n1647年にイギリスが植民地化を開始する。\n1718年にイギリスは、「黒髭」と呼ばれたエドワード・ティーチ (Edward Teach) をはじめとする海賊たちの拠点であったバハマに対し、ウッズ・ロジャーズ (Woodes Rogers) を初代総督(Royal Governor of the Bahamas) に任じ掃討を命じた。\n1776年に、アメリカ独立戦争から逃れようとしたイギリス王党派が、多くの黒人奴隷を引き連れて移り住む。\n1782年から83年にかけて、スペインに占領される。しかし、領有権を取り戻したイギリスは、その年に奴隷を解放。\n1783年、ヴェルサイユ条約において正式にイギリス領と認められる。\n1920年から1933年までは、アメリカで禁酒法が制定され、これにより、バハマは酒などの密輸の一大中心地となった。\n1940年から1945年まで、ウィンザー公（元イギリス国王エドワード8世）がバハマ総督を務める。\n1945年以後、反植民地運動が起こった。\n1964年1月7日、自治権獲得。\n1969年、\"Commonwealth of the Bahama Islands\" に改称。\n1973年7月10日、独立。国名を \"Commonwealth of The Bahamas\" とする。英連邦王国の一国として独立した。\n1976年に商船用に便宜置籍国の国旗を設置。\n1983年、バハマ政府が関与した麻薬密輸のスキャンダルが発覚。\n1981-1986年、バンク・ロイのバハマ支店をドレクセル・バーナム・ランバートのデニス・レヴィーンがインサイダー取引に利用。\n1987年、総選挙でも麻薬密売に関するスキャンダルを乗り越え、与党が大勝した。\n1992年、英領時代から25年以上続いた進歩自由党のリンデン・ピンドリング政権が自由国民運動のヒューバート・イングラハム政権に交代。以降は両党による政権交代を繰り返している。\n\n\n== 政治 ==\n\n\n=== 内政 ===\n\nイギリスの国王を君主とし、総督をその代理人とする、立憲君主制。首相は、与党の党首が総督によって任命される、議院内閣制である。\n議会は、両院制（二院制）。民選議員で構成される下院（38議席）と、首相と野党党首の推薦により総督が任命する議員で構成される上院（16議席）から成る。両院とも任期は5年。1973年の独立以来、進歩自由党(PLP)と自由国民運動(FNM)による二大政党制となっており、直近の2021年、2026年の総選挙では、PLPが圧勝し政権を担っている。\n\n\n== 国際関係 ==\n\n\n=== 日本との関係 ===\n\n\n== 国家安全保障 ==\n\n王立バハマ国防軍(Royal Bahamas Defence Force：RBDF)がある。軍は海軍（実質的には沿岸警備隊）のみで編成されており、2007年現在、現役兵約860人が所属し、志願制を採用している。経済水域の警備や捜索救難の他に、麻薬密輸対策やキューバ難民の監視も重要な任務となっている。また、ガイアナ沿岸警備隊がニュープロビデンス島内に基地を設けている。\n\n\n== 地方行政区分 ==\n\n33の県 (district) に分かれる。\n\n\n== 地理 ==\n\nバハマ諸島は約700の島々と2,400の岩礁からなるほぼサンゴ礁の群島である。うち、30の島々に人が住む。ニュー・プロビデンス島にはバハマの首都ナッソーがある。また、水面積率が世界1位。\n\nバハマ諸島の主な島々\nアンドロス島\nイナグア島\nエルーセラ島\nキャスタウェイ・ケイ\nグランド・バハマ島\nサン・サルバドル島\nダブル・ヘディッド・ショット諸島\nニュー・プロビデンス島\nビミニ\nベリー諸島\n\n\n== 経済 ==\n観光業とタックス・ヘイヴンなどの金融業が経済の中心である。首都・ナッソーを始めカジノに興ずる観光客も多い。旧イギリス領であることから、日本と同様に車は左側通行であるが、地理的にアメリカ合衆国からの輸入車が多く、左ハンドル車が多く見かけられる。\n2019年度GDPは131億6400万ドル、1人あたりは3万4575.624ドルとなっている（為替レート）。\n\n\n=== バハマ文書 ===\n2016年9月にはバハマ文書（実態のない会社を設立・運用した租税回避行為に関する文書）の公開によって、バハマにペーパーカンパニーを設立していた企業や個人名が公開され、注目を集めた。\n\n\n== 国民 ==\n\n人種構成は、アフリカ系黒人が 85%、白人が 12%、アジアやラテンアメリカ系人が 3%。\n宗教は、バプティスト 32%、英国国教会 20%、ローマ・カトリック教会 19%、メソジスト 6%、チャーチ・オブ・ゴッド 6%、他のプロテスタント 12%、その他が2%、無宗教または不明が3%。\n使用言語は、公用語となっている英語の他に、クレオール語がハイチからの移民者の間では使われている。\n\n\n== 文化 ==\n\nバハマ諸島の文化は、アフリカ（アフリカ系バハマ人は国内最大のエスニシティである）、イギリス、アメリカの諸文化が歴史的な経緯で混淆したものである。特にアメリカからは、古くは解放奴隷の移住、のちには観光客の流入などを通して多大な影響を受けてきた。\nバハマにはファミリー諸島を中心として、アフリカに起源を持つ魔術の伝統がいまも残る。ただし、バハマ国内でオビア（呪術）の実践は違法で、法により処罰される。\nファミリー諸島ではまた、ヤシの葉からバスケットなどの工芸品がつくられている。一般に「わら」と呼ばれるヤシの葉からは帽子やバッグもつくられ、観光客に人気のみやげ品となっている。\nナッソーほか数か所の町では、毎年ボクシング・デーや元日になるとジャンカヌーというアフリカ系の伝統的なパレードが行われる。奴隷解放記念日など、ほかの祝日に開催されることもある。\nファミリー諸島の多くの町や村にとって、レガッタ競走は重要なイベントである。レガッタ競走にはたいてい昔ながらの作業船が使用され、一日もしくは数日続く。\n\n\n=== 食文化 ===\n\n食文化にもカリブ、アフリカ、ヨーロッパの各文化の影響がみられる。グレゴリータウンのパイナップル・フェストやアンドロスのクラブ・フェストなど、祭事のときだけつくられる独特の料理が各地に伝わっている。\n\n\n=== 音楽 ===\n\nソカ（トリニダード・トバゴ発祥）\nカリプソ（トリニダード・トバゴ発祥）\nジャンカヌー\nロニー・バトラー\nレークン・スクラップ\nバハ・メン - Who Let the Dogs Out?がグラミー賞を受賞。\nグームベイ - ブレーク・アルフォンソ・ヒッグスなどの奏者が有名。\n\n\n=== 祝祭日 ===\n\n\n== スポーツ ==\n\n\n=== サッカー ===\n\nバハマサッカー連盟によって構成されるサッカーバハマ代表は、FIFAワールドカップおよびCONCACAFゴールドカップ、さらにはカリビアンカップへの出場経験は1度もない。また、1990年にはサッカーリーグのBFAシニアリーグも創設されている。\n\n\n=== バスケットボール ===\nバスケットボールバハマ代表はオリンピックおよびFIBAバスケットボール・ワールドカップには未出場であり、FIBAアメリカップには1995年大会に1度出場したのみである。しかし、FIBAカリブ海選手権では歴代最多となる優勝7度を記録している。また、バハマからは計6人のNBAプレイヤーも輩出している。\n\n\n=== 野球 ===\n大洋ホエールズでもプレーしたアンディ・ロジャースを皮切りに、8人のメジャーリーガーを輩出している。現役ではジャズ・チザム・ジュニアとルーシャス・フォックスがプレーしている。\n\n\n== 著名な出身者 ==\n\n\n== 脚注 ==\n\n\n== 関連項目 ==\n\nバハマ諸島\nバハマ文書\nバハマ時間\n\n\n== 外部リンク ==\n政府\nバハマ国政府　 （英語）\nバハマ観光省 （英語）\n日本政府\nバハマ国 - 日本外務省（日本語）\n在バハマ日本国大使館 （日本語）"
}